examples/__init__.py
examples/run_all_steps.py
examples/scenarios.py
examples/step1.py
examples/step2.py
examples/step3.py
examples/step4.py
examples/unit_tests_example0.py
examples/unit_tests_example0_1.py
examples/unit_tests_example0_2.py
examples/unit_tests_example0_3.py
examples/unit_tests_example0_4.py
examples/unit_tests_example1.py
examples/unit_tests_example2.py
unit_test_advanced/UnitTest.py
unit_test_advanced/UnitTestAction.py
unit_test_advanced/__init__.py
unit_test_advanced/functools.py
unit_test_advanced-0.1.8.dist-info/AUTHORS
unit_test_advanced-0.1.8.dist-info/LICENSE
unit_test_advanced-0.1.8.dist-info/METADATA
unit_test_advanced-0.1.8.dist-info/WHEEL
unit_test_advanced-0.1.8.dist-info/top_level.txt
unit_test_advanced-0.1.8.dist-info/RECORD
