Metadata-Version: 2.1
Name: unit_test_advanced
Version: 0.1.8
Summary: Program execution plans for unit testing and inject custom data
Home-page: https://github.com/roodrepo/unit_test_advanced
Author: Rood Repo
Author-email: roodrepo@gmail.com
License: UNKNOWN
Keywords: unit-test,inject data,test driven development
Platform: UNKNOWN
Classifier: Programming Language :: Python :: 3
Classifier: License :: OSI Approved :: MIT License
Classifier: Intended Audience :: Developers
Classifier: Operating System :: OS Independent
Requires-Python: >=3.7
License-File: LICENSE
License-File: AUTHORS
